immunonaut/__init__.py
immunonaut/__main__.py
immunonaut/cell_types.py
immunonaut/core/__init__.py
immunonaut/core/coretypes.py
immunonaut/models/__init__.py
immunonaut/models/human.py
immunonaut/pathways/_protocols.py
immunonaut/pathways/antigens.py
immunonaut/pathways/cytokines.py
immunonaut/pathways/enzymes.py
immunonaut/pathways/human_pathways.py
immunonaut/pathways/main.py
immunonaut/pathways/mapping.py
immunonaut/pathways/proteins.py
immunonaut/pathways/targets.py
immunonaut/responses/__init__.py
immunonaut/responses/_protocols.py
immunonaut/responses/acute.py
immunonaut-0.0.2.dist-info/LICENSE
immunonaut-0.0.2.dist-info/METADATA
immunonaut-0.0.2.dist-info/WHEEL
immunonaut-0.0.2.dist-info/RECORD
